twitter.common.rpc-0.3.11-py2.7-nspkg.pth
twitter/common/rpc/__init__.py
twitter/common/rpc/address.py
twitter/common/rpc/factories.py
twitter/common/rpc/sasl/__init__.py
twitter/common/rpc/sasl/transport.py
twitter/common/rpc/transports/__init__.py
twitter/common/rpc/transports/tsslsocket.py
twitter.common.rpc-0.3.11.dist-info/DESCRIPTION.rst
twitter.common.rpc-0.3.11.dist-info/METADATA
twitter.common.rpc-0.3.11.dist-info/RECORD
twitter.common.rpc-0.3.11.dist-info/WHEEL
twitter.common.rpc-0.3.11.dist-info/metadata.json
twitter.common.rpc-0.3.11.dist-info/namespace_packages.txt
twitter.common.rpc-0.3.11.dist-info/top_level.txt
twitter.common.rpc-0.3.11.dist-info/zip-safe
